{
    "states": [
        { "id": "RJ", "name": "Rajasthan" },
        { "id": "KA", "name": "Karnataka" },
        { "id": "MH", "name": "Maharashtra" }
      ],
      "divisions": [
        { "id": "JPR", "name": "Jaipur", "stateId": "RJ" },
        { "id": "JDP", "name": "Jodhpur", "stateId": "RJ" },
        { "id": "UDP", "name": "Udaipur", "stateId": "RJ" },
        { "id": "BLR", "name": "Bangalore", "stateId": "KA" },
        { "id": "MYS", "name": "Mysore", "stateId": "KA" },
        { "id": "HBL", "name": "Hubli", "stateId": "KA" },
        { "id": "MUM", "name": "Mumbai", "stateId": "MH" },
        { "id": "PUN", "name": "Pune", "stateId": "MH" },
        { "id": "NAG", "name": "Nagpur", "stateId": "MH" }
      ],
"districts": [
   
    { "id": "JPR-D", "name": "Jaipur", "divisionId": "JPR" },
    { "id": "ALW", "name": "Alwar", "divisionId": "JPR" },
    { "id": "SKR", "name": "Sikar", "divisionId": "JPR" },

   
    { "id": "JDP-D", "name": "Jodhpur", "divisionId": "JDP" },
    { "id": "BAR", "name": "Barmer", "divisionId": "JDP" },
    { "id": "JSL", "name": "Jaisalmer", "divisionId": "JDP" },

   
    { "id": "UDP-D", "name": "Udaipur", "divisionId": "UDP" },
    { "id": "BNS", "name": "Banswara", "divisionId": "UDP" },
    { "id": "DDR", "name": "Dungarpur", "divisionId": "UDP" },

   
    { "id": "BLR-D", "name": "Bangalore Urban", "divisionId": "BLR" },
    { "id": "BLR-R", "name": "Bangalore Rural", "divisionId": "BLR" },
    { "id": "KLR", "name": "Kolar", "divisionId": "BLR" },

    
    { "id": "MYS-D", "name": "Mysore", "divisionId": "MYS" },
    { "id": "MDR", "name": "Mandya", "divisionId": "MYS" },
    { "id": "CTK", "name": "Chitradurga", "divisionId": "MYS" },

    
    { "id": "MUM-D", "name": "Mumbai", "divisionId": "MUM" },
    { "id": "THN", "name": "Thane", "divisionId": "MUM" },
    { "id": "PLG", "name": "Palghar", "divisionId": "MUM" },

    
    { "id": "PUN-D", "name": "Pune", "divisionId": "PUN" },
    { "id": "SAT", "name": "Satara", "divisionId": "PUN" },
    { "id": "SLP", "name": "Solapur", "divisionId": "PUN" },

    
    { "id": "NAG-D", "name": "Nagpur", "divisionId": "NAG" },
    { "id": "WAR", "name": "Wardha", "divisionId": "NAG" },
    { "id": "AMR", "name": "Amravati", "divisionId": "NAG" }
  ],

  "blocks": [
    
    { "id": "BAS", "name": "Bassi", "districtId": "JPR-D" },
    { "id": "CHK", "name": "Chaksu", "districtId": "JPR-D" },
    { "id": "SNG", "name": "Sanganer", "districtId": "JPR-D" },

   
    { "id": "MDR", "name": "Mandore", "districtId": "JDP-D" },
    { "id": "LSN", "name": "Luni", "districtId": "JDP-D" },

   
    { "id": "GIR", "name": "Girwa", "districtId": "UDP-D" },
    { "id": "SLM", "name": "Salumber", "districtId": "UDP-D" },

    
    { "id": "HSR", "name": "HSR Layout", "districtId": "BLR-D" },
    { "id": "IND", "name": "Indiranagar", "districtId": "BLR-D" },

   
    { "id": "YEL", "name": "Yelahanka", "districtId": "BLR-R" },
    { "id": "DNB", "name": "Devanahalli", "districtId": "BLR-R" },

   
    { "id": "WAN", "name": "Wagholi", "districtId": "PUN-D" },
    { "id": "HAD", "name": "Hadapsar", "districtId": "PUN-D" },
    { "id": "KOT", "name": "Kothrud", "districtId": "PUN-D" },

   
    { "id": "KRA", "name": "Karad", "districtId": "SAT" },
    { "id": "PAT", "name": "Patan", "districtId": "SAT" },

    
    { "id": "HGN", "name": "Hingna", "districtId": "NAG-D" },
    { "id": "KRD", "name": "Kalmeshwar", "districtId": "NAG-D" }
  ],

  "sectors": [
   
    { "id": "BAS-S1", "name": "Sector 1", "blockId": "BAS" },
    { "id": "BAS-S2", "name": "Sector 2", "blockId": "BAS" },

   
    { "id": "CHK-S1", "name": "Sector 1", "blockId": "CHK" },

    
    { "id": "MDR-S1", "name": "Sector 1", "blockId": "MDR" },

   
    { "id": "GIR-S1", "name": "Sector 1", "blockId": "GIR" },
    { "id": "GIR-S2", "name": "Sector 2", "blockId": "GIR" },

   
    { "id": "YEL-S1", "name": "Sector A", "blockId": "YEL" },
    { "id": "YEL-S2", "name": "Sector B", "blockId": "YEL" },

    
    { "id": "HSR-S1", "name": "Sector 1", "blockId": "HSR" },
    { "id": "HSR-S2", "name": "Sector 2", "blockId": "HSR" },

    
    { "id": "WAN-S1", "name": "Sector 1", "blockId": "WAN" },
    { "id": "WAN-S2", "name": "Sector 2", "blockId": "WAN" },

   
    { "id": "HGN-S1", "name": "Sector 1", "blockId": "HGN" },
    { "id": "HGN-S2", "name": "Sector 2", "blockId": "HGN" }
  ],
    "organizationTypes": [
        { "id": "DMH", "name": "Director - MH", "stateId": "RJ" },
        { "id": "DCH", "name": "Director - CH", "stateId": "RJ" },
        { "id": "DFW", "name": "Director - FW", "stateId": "RJ" },
        { "id": "DKH", "name": "Director - KH", "stateId": "KA" },
        { "id": "DWH", "name": "Director - WH", "stateId": "KA" },
        { "id": "DKH-MH", "name": "Director - KH MH", "stateId": "MH" }
      ],
      "designations": [
        { "id": "PDMH", "name": "Project Director - MH", "orgTypeId": "DMH" },
        { "id": "DDMH", "name": "Deputy Director - MH", "orgTypeId": "DMH" },
        { "id": "ADMH", "name": "Assistant Director - MH", "orgTypeId": "DMH" },
        { "id": "PDCH", "name": "Project Director - CH", "orgTypeId": "DCH" },
        { "id": "DDCH", "name": "Deputy Director - CH", "orgTypeId": "DCH" },
        { "id": "PDFW", "name": "Project Director - FW", "orgTypeId": "DFW" },
        { "id": "PDKH", "name": "Project Director - KH", "orgTypeId": "DKH" },
        { "id": "PDWH", "name": "Project Director - WH", "orgTypeId": "DWH" },
        { "id": "PDKMH", "name": "Project Director - KH MH", "orgTypeId": "DKH-MH" }
      ]
    
  }
  